gdmec23120358/__init__.py
gdmec23120358-0.1.2.dist-info/METADATA
gdmec23120358-0.1.2.dist-info/WHEEL
gdmec23120358-0.1.2.dist-info/entry_points.txt
gdmec23120358-0.1.2.dist-info/RECORD
